{"cameraMode":{"drawMode":0,"name":"Shaded","section":"Shading Mode"},"sceneLighting":true,"audioPlay":false,"sceneViewState":{"showFog":true,"showMaterialUpdate":false,"showSkybox":true,"showFlares":true,"showImageEffects":true,"showParticleSystems":true},"in2DMode":false,"pivot":{"x":0.6406605839729309,"y":1.7925446033477784,"z":-0.6818450689315796},"rotation":{"x":-0.06534486263990402,"y":0.02304605022072792,"z":-0.001403646543622017,"w":-0.9977002739906311},"size":1.2998411655426026,"orthographic":false}